calcrule_unconditional_cash_payment/__init__.py
calcrule_unconditional_cash_payment/admin.py
calcrule_unconditional_cash_payment/apps.py
calcrule_unconditional_cash_payment/calculation_rule.py
calcrule_unconditional_cash_payment/config.py
calcrule_unconditional_cash_payment/models.py
calcrule_unconditional_cash_payment/signals.py
calcrule_unconditional_cash_payment/tests.py
calcrule_unconditional_cash_payment/urls.py
calcrule_unconditional_cash_payment/views.py
calcrule_unconditional_cash_payment/converters/__init__.py
calcrule_unconditional_cash_payment/converters/policy_to_bill.py
calcrule_unconditional_cash_payment/converters/policy_to_bill_item.py
calcrule_unconditional_cash_payment/migrations/__init__.py
openimis_be_calcrule_unconditional_cash_payment-1.6.1.dist-info/LICENSE.md
openimis_be_calcrule_unconditional_cash_payment-1.6.1.dist-info/METADATA
openimis_be_calcrule_unconditional_cash_payment-1.6.1.dist-info/WHEEL
openimis_be_calcrule_unconditional_cash_payment-1.6.1.dist-info/top_level.txt
openimis_be_calcrule_unconditional_cash_payment-1.6.1.dist-info/RECORD
