Metadata-Version: 2.1
Name: openimis-be-calcrule_unconditional_cash_payment
Version: 1.6.1
Summary: The openIMIS Backend calcrule_unconditional_cash_payment reference module.
Home-page: https://openimis.org/
Author: Wojciech Zgliniecki
Author-email: wzgliniecki@soldevelo.com
License: GNU AGPL v3
Classifier: Environment :: Web Environment
Classifier: Framework :: Django
Classifier: Framework :: Django :: 3.0
Classifier: Intended Audience :: Developers
Classifier: License :: OSI Approved :: GNU Affero General Public License v3
Classifier: Operating System :: OS Independent
Classifier: Programming Language :: Python
Classifier: Programming Language :: Python :: 3.8
License-File: LICENSE.md
Requires-Dist: django
Requires-Dist: django-db-signals
Requires-Dist: djangorestframework
Requires-Dist: openimis-be-core
